rtl/UART_TX.v
module UART_TX#(parameter N = 8)                            // N = packet size
    (
    /* PORTLIST */
    output  reg         tx_o,
    output              tx_done,
    
    input   [N-1:0]     data_i,
    input               data_we_i,

    input               tx_en_i,
                        tick_i, 
                        clk_i,
                        rst_i
    );

    parameter   IDLE            = 0,
                TRANSMITTING    = 1; 

    initial             tx_o    = 1;
    
    assign tx_done = ~state;

    /*
        Input data is registered
    */
    reg     [N-1:0]     data = 0;
    always @(posedge clk_i) begin
        if(rst_i)
            data <= 0;
        else if(data_we_i)
            data <= data_i;
    end
    

    /*
        data_valid flag is used to indicate arrival 
        of fresh input data
    */
    reg data_valid = 0;
    always @(posedge clk_i) begin
        if(rst_i)
            data_valid <= 0;
        else if(data_we_i)
            data_valid <= 1;
        if(stop_bit_cond)
            data_valid <= 0;    // data_valid is cleared after successful transmission 
    end
    


    // state register
    reg state   = IDLE;


    /////////////////////// STATE Machine //////////////////////
    /*
        Controls state transitions
    */
    always @ (posedge clk_i) begin
        if(rst_i)
            state <= IDLE;
        else
            state <= next(state, tx_en_i, data_valid, stop_bit_cond);
    end

    /*
        Next state decision (combinational logic)
    */
    function next;
        input state;
        input tx_en_i;
        input data_valid;
        input stop_bit_cond;
        
        begin
            case(state)
                IDLE:           if(data_valid & tx_en_i)    next = TRANSMITTING;
                                else                        next = IDLE;
                
                TRANSMITTING:   if(stop_bit_cond)           next = IDLE;
                                else                        next = TRANSMITTING;

                default:                                    next = IDLE;
            endcase
        end
    endfunction 

    reg [4:0]           counter     = 0;
    reg [$clog2(N):0]   bitcount    = 0;

    /*
        rx_i        |``````````````\......../````````\................/`````````\................/````````````````````````````````
                    |      |        |        |        |        |        |        |        |        |        |        |        |
                                start bit    D7       D6       D5       D4       D3       D2       D1       D0    stop bit
        
        bitcount    <      0        ><   1   ><   2   ><   3   ><   4   ><    5  ><   6   ><   7   ><   8   ><   9   ><   0   ><
    */

    wire start_bit_cond     = (counter == 1)   &   (bitcount == 0);
    wire data_bit_cond      = (counter == 15)   &   (bitcount <= N);
    wire stop_bit_cond      = (counter == 15)   &   (bitcount == N+1);   



    // counter
    always @ (posedge tick_i)begin
        if(state == TRANSMITTING) begin
            if(start_bit_cond | data_bit_cond)
                counter <= 0;

            else 
                counter <= counter +1;
        end
        if(stop_bit_cond)
                counter <= 0;        
    end

    // bitcount
    always @ (posedge tick_i)begin
        if(state == TRANSMITTING)begin
            if(start_bit_cond | data_bit_cond)
                bitcount <= bitcount+1;            
            
        end
        if(stop_bit_cond)
                bitcount <= 0;
    end

    // data
    always @ (posedge tick_i)begin
        if(state == TRANSMITTING)begin
            if(data_bit_cond)
                data <=  (data << 1);  // Shift data register
        end
        if(stop_bit_cond)
                data <= 0;
    end

    // tx_o
    always @ (posedge tick_i)begin
        if(state == TRANSMITTING)begin
            if(start_bit_cond)
                tx_o <= 0;
            if(data_bit_cond)
                tx_o <= data[N-1];      
        end
        if(stop_bit_cond)
                tx_o <= 1;              
    end


endmodule

rtl/Uart_Tx_tb.v
`timescale 1ns/10ps
`include "UART_TX.v"

module Uart_Tx_tb;
    reg clk_master;
    reg tick;
    wire chng;
    reg [3:0] tick_counter;
    
    reg  tx_en = 1;    
    reg rst_i = 0;

    wire tx_o;
    wire tx_done;

    reg [7:0] data_i;
    reg       data_we_i;


    UART_TX utx
    (
    /* PORTLIST */
    tx_o,
    tx_done,
    
    data_i,
    data_we_i,

    tx_en,
    tick, 
    clk_master,
    rst_i
    );

    initial begin
        clk_master = 0;tick = 0; tx_en = 0; data_i = 0; data_we_i = 0;
        tick_counter = 0;
        $dumpfile("out_tx.vcd");
        $dumpvars(0, Uart_Tx_tb);
        
        #700;
        data_i = 8'b11011010;
        data_we_i = 1; #4
        data_we_i = 0;
        #100;
        tx_en = 1;

        #5000;
        tx_en = 0;
        #5000;

        data_i = 8'b00101101;
        data_we_i = 1; #4
        data_we_i = 0;
        #5000;
        tx_en = 1;

        #10000;
        

        #10000;
        $finish();
    end




    // change
    always@(posedge tick) begin
        tick_counter <= tick_counter+1;
    end

    assign chng = (tick_counter == 15);

    
    // tick
    reg [2:0] clk_counter = 0;

    always@(posedge clk_master) begin
        clk_counter <= clk_counter+1;
    end
    wire ctr_chng = (clk_counter == 3);

    always@(posedge ctr_chng) begin
        tick <= ~tick;
    end

    // master clk
    always begin
        #1;
        clk_master <= ~clk_master;
    end
    
endmodule

rtl/out_tx.vcd
$date
	Wed Feb  3 12:38:33 2021
$end
$version
	Icarus Verilog
$end
$timescale
	10ps
$end
$scope module Uart_Tx_tb $end
$var wire 1 ! tx_o $end
$var wire 1 " tx_done $end
$var wire 1 # ctr_chng $end
$var wire 1 $ chng $end
$var reg 3 % clk_counter [2:0] $end
$var reg 1 & clk_master $end
$var reg 8 ' data_i [7:0] $end
$var reg 1 ( data_we_i $end
$var reg 1 ) rst_i $end
$var reg 1 * tick $end
$var reg 4 + tick_counter [3:0] $end
$var reg 1 , tx_en $end
$scope module utx $end
$var wire 1 & clk_i $end
$var wire 1 - data_bit_cond $end
$var wire 8 . data_i [7:0] $end
$var wire 1 ( data_we_i $end
$var wire 1 ) rst_i $end
$var wire 1 / start_bit_cond $end
$var wire 1 0 stop_bit_cond $end
$var wire 1 * tick_i $end
$var wire 1 " tx_done $end
$var wire 1 , tx_en_i $end
$var reg 4 1 bitcount [3:0] $end
$var reg 5 2 counter [4:0] $end
$var reg 8 3 data [7:0] $end
$var reg 1 4 data_valid $end
$var reg 1 5 state $end
$var reg 1 ! tx_o $end
$scope function next $end
$var reg 1 6 data_valid $end
$var reg 1 7 next $end
$var reg 1 8 state $end
$var reg 1 9 stop_bit_cond $end
$var reg 1 : tx_en_i $end
$upscope $end
$upscope $end
$upscope $end
$enddefinitions $end
#0
$dumpvars
x:
x9
x8
x7
x6
05
04
b0 3
b0 2
b0 1
00
0/
b0 .
0-
0,
b0 +
0*
0)
0(
b0 '
0&
b0 %
0$
0#
1"
1!
$end
#100
b1 %
07
08
0:
06
09
1&
#200
0&
#300
b10 %
1&
#400
0&
#500
b1 +
1*
1#
b11 %
1&
#600
0&
#700
0#
b100 %
1&
#800
0&
#900
b101 %
1&
#1000
0&
#1100
b110 %
1&
#1200
0&
#1300
b111 %
1&
#1400
0&
#1500
b0 %
1&
#1600
0&
#1700
b1 %
1&
#1800
0&
#1900
b10 %
1&
#2000
0&
#2100
0*
1#
b11 %
1&
#2200
0&
#2300
0#
b100 %
1&
#2400
0&
#2500
b101 %
1&
#2600
0&
#2700
b110 %
1&
#2800
0&
#2900
b111 %
1&
#3000
0&
#3100
b0 %
1&
#3200
0&
#3300
b1 %
1&
#3400
0&
#3500
b10 %
1&
#3600
0&
#3700
b10 +
1*
1#
b11 %
1&
#3800
0&
#3900
0#
b100 %
1&
#4000
0&
#4100
b101 %
1&
#4200
0&
#4300
b110 %
1&
#4400
0&
#4500
b111 %
1&
#4600
0&
#4700
b0 %
1&
#4800
0&
#4900
b1 %
1&
#5000
0&
#5100
b10 %
1&
#5200
0&
#5300
0*
1#
b11 %
1&
#5400
0&
#5500
0#
b100 %
1&
#5600
0&
#5700
b101 %
1&
#5800
0&
#5900
b110 %
1&
#6000
0&
#6100
b111 %
1&
#6200
0&
#6300
b0 %
1&
#6400
0&
#6500
b1 %
1&
#6600
0&
#6700
b10 %
1&
#6800
0&
#6900
b11 +
1*
1#
b11 %
1&
#7000
0&
#7100
0#
b100 %
1&
#7200
0&
#7300
b101 %
1&
#7400
0&
#7500
b110 %
1&
#7600
0&
#7700
b111 %
1&
#7800
0&
#7900
b0 %
1&
#8000
0&
#8100
b1 %
1&
#8200
0&
#8300
b10 %
1&
#8400
0&
#8500
0*
1#
b11 %
1&
#8600
0&
#8700
0#
b100 %
1&
#8800
0&
#8900
b101 %
1&
#9000
0&
#9100
b110 %
1&
#9200
0&
#9300
b111 %
1&
#9400
0&
#9500
b0 %
1&
#9600
0&
#9700
b1 %
1&
#9800
0&
#9900
b10 %
1&
#10000
0&
#10100
b100 +
1*
1#
b11 %
1&
#10200
0&
#10300
0#
b100 %
1&
#10400
0&
#10500
b101 %
1&
#10600
0&
#10700
b110 %
1&
#10800
0&
#10900
b111 %
1&
#11000
0&
#11100
b0 %
1&
#11200
0&
#11300
b1 %
1&
#11400
0&
#11500
b10 %
1&
#11600
0&
#11700
0*
1#
b11 %
1&
#11800
0&
#11900
0#
b100 %
1&
#12000
0&
#12100
b101 %
1&
#12200
0&
#12300
b110 %
1&
#12400
0&
#12500
b111 %
1&
#12600
0&
#12700
b0 %
1&
#12800
0&
#12900
b1 %
1&
#13000
0&
#13100
b10 %
1&
#13200
0&
#13300
b101 +
1*
1#
b11 %
1&
#13400
0&
#13500
0#
b100 %
1&
#13600
0&
#13700
b101 %
1&
#13800
0&
#13900
b110 %
1&
#14000
0&
#14100
b111 %
1&
#14200
0&
#14300
b0 %
1&
#14400
0&
#14500
b1 %
1&
#14600
0&
#14700
b10 %
1&
#14800
0&
#14900
0*
1#
b11 %
1&
#15000
0&
#15100
0#
b100 %
1&
#15200
0&
#15300
b101 %
1&
#15400
0&
#15500
b110 %
1&
#15600
0&
#15700
b111 %
1&
#15800
0&
#15900
b0 %
1&
#16000
0&
#16100
b1 %
1&
#16200
0&
#16300
b10 %
1&
#16400
0&
#16500
b110 +
1*
1#
b11 %
1&
#16600
0&
#16700
0#
b100 %
1&
#16800
0&
#16900
b101 %
1&
#17000
0&
#17100
b110 %
1&
#17200
0&
#17300
b111 %
1&
#17400
0&
#17500
b0 %
1&
#17600
0&
#17700
b1 %
1&
#17800
0&
#17900
b10 %
1&
#18000
0&
#18100
0*
1#
b11 %
1&
#18200
0&
#18300
0#
b100 %
1&
#18400
0&
#18500
b101 %
1&
#18600
0&
#18700
b110 %
1&
#18800
0&
#18900
b111 %
1&
#19000
0&
#19100
b0 %
1&
#19200
0&
#19300
b1 %
1&
#19400
0&
#19500
b10 %
1&
#19600
0&
#19700
b111 +
1*
1#
b11 %
1&
#19800
0&
#19900
0#
b100 %
1&
#20000
0&
#20100
b101 %
1&
#20200
0&
#20300
b110 %
1&
#20400
0&
#20500
b111 %
1&
#20600
0&
#20700
b0 %
1&
#20800
0&
#20900
b1 %
1&
#21000
0&
#21100
b10 %
1&
#21200
0&
#21300
0*
1#
b11 %
1&
#21400
0&
#21500
0#
b100 %
1&
#21600
0&
#21700
b101 %
1&
#21800
0&
#21900
b110 %
1&
#22000
0&
#22100
b111 %
1&
#22200
0&
#22300
b0 %
1&
#22400
0&
#22500
b1 %
1&
#22600
0&
#22700
b10 %
1&
#22800
0&
#22900
b1000 +
1*
1#
b11 %
1&
#23000
0&
#23100
0#
b100 %
1&
#23200
0&
#23300
b101 %
1&
#23400
0&
#23500
b110 %
1&
#23600
0&
#23700
b111 %
1&
#23800
0&
#23900
b0 %
1&
#24000
0&
#24100
b1 %
1&
#24200
0&
#24300
b10 %
1&
#24400
0&
#24500
0*
1#
b11 %
1&
#24600
0&
#24700
0#
b100 %
1&
#24800
0&
#24900
b101 %
1&
#25000
0&
#25100
b110 %
1&
#25200
0&
#25300
b111 %
1&
#25400
0&
#25500
b0 %
1&
#25600
0&
#25700
b1 %
1&
#25800
0&
#25900
b10 %
1&
#26000
0&
#26100
b1001 +
1*
1#
b11 %
1&
#26200
0&
#26300
0#
b100 %
1&
#26400
0&
#26500
b101 %
1&
#26600
0&
#26700
b110 %
1&
#26800
0&
#26900
b111 %
1&
#27000
0&
#27100
b0 %
1&
#27200
0&
#27300
b1 %
1&
#27400
0&
#27500
b10 %
1&
#27600
0&
#27700
0*
1#
b11 %
1&
#27800
0&
#27900
0#
b100 %
1&
#28000
0&
#28100
b101 %
1&
#28200
0&
#28300
b110 %
1&
#28400
0&
#28500
b111 %
1&
#28600
0&
#28700
b0 %
1&
#28800
0&
#28900
b1 %
1&
#29000
0&
#29100
b10 %
1&
#29200
0&
#29300
b1010 +
1*
1#
b11 %
1&
#29400
0&
#29500
0#
b100 %
1&
#29600
0&
#29700
b101 %
1&
#29800
0&
#29900
b110 %
1&
#30000
0&
#30100
b111 %
1&
#30200
0&
#30300
b0 %
1&
#30400
0&
#30500
b1 %
1&
#30600
0&
#30700
b10 %
1&
#30800
0&
#30900
0*
1#
b11 %
1&
#31000
0&
#31100
0#
b100 %
1&
#31200
0&
#31300
b101 %
1&
#31400
0&
#31500
b110 %
1&
#31600
0&
#31700
b111 %
1&
#31800
0&
#31900
b0 %
1&
#32000
0&
#32100
b1 %
1&
#32200
0&
#32300
b10 %
1&
#32400
0&
#32500
b1011 +
1*
1#
b11 %
1&
#32600
0&
#32700
0#
b100 %
1&
#32800
0&
#32900
b101 %
1&
#33000
0&
#33100
b110 %
1&
#33200
0&
#33300
b111 %
1&
#33400
0&
#33500
b0 %
1&
#33600
0&
#33700
b1 %
1&
#33800
0&
#33900
b10 %
1&
#34000
0&
#34100
0*
1#
b11 %
1&
#34200
0&
#34300
0#
b100 %
1&
#34400
0&
#34500
b101 %
1&
#34600
0&
#34700
b110 %
1&
#34800
0&
#34900
b111 %
1&
#35000
0&
#35100
b0 %
1&
#35200
0&
#35300
b1 %
1&
#35400
0&
#35500
b10 %
1&
#35600
0&
#35700
b1100 +
1*
1#
b11 %
1&
#35800
0&
#35900
0#
b100 %
1&
#36000
0&
#36100
b101 %
1&
#36200
0&
#36300
b110 %
1&
#36400
0&
#36500
b111 %
1&
#36600
0&
#36700
b0 %
1&
#36800
0&
#36900
b1 %
1&
#37000
0&
#37100
b10 %
1&
#37200
0&
#37300
0*
1#
b11 %
1&
#37400
0&
#37500
0#
b100 %
1&
#37600
0&
#37700
b101 %
1&
#37800
0&
#37900
b110 %
1&
#38000
0&
#38100
b111 %
1&
#38200
0&
#38300
b0 %
1&
#38400
0&
#38500
b1 %
1&
#38600
0&
#38700
b10 %
1&
#38800
0&
#38900
b1101 +
1*
1#
b11 %
1&
#39000
0&
#39100
0#
b100 %
1&
#39200
0&
#39300
b101 %
1&
#39400
0&
#39500
b110 %
1&
#39600
0&
#39700
b111 %
1&
#39800
0&
#39900
b0 %
1&
#40000
0&
#40100
b1 %
1&
#40200
0&
#40300
b10 %
1&
#40400
0&
#40500
0*
1#
b11 %
1&
#40600
0&
#40700
0#
b100 %
1&
#40800
0&
#40900
b101 %
1&
#41000
0&
#41100
b110 %
1&
#41200
0&
#41300
b111 %
1&
#41400
0&
#41500
b0 %
1&
#41600
0&
#41700
b1 %
1&
#41800
0&
#41900
b10 %
1&
#42000
0&
#42100
b1110 +
1*
1#
b11 %
1&
#42200
0&
#42300
0#
b100 %
1&
#42400
0&
#42500
b101 %
1&
#42600
0&
#42700
b110 %
1&
#42800
0&
#42900
b111 %
1&
#43000
0&
#43100
b0 %
1&
#43200
0&
#43300
b1 %
1&
#43400
0&
#43500
b10 %
1&
#43600
0&
#43700
0*
1#
b11 %
1&
#43800
0&
#43900
0#
b100 %
1&
#44000
0&
#44100
b101 %
1&
#44200
0&
#44300
b110 %
1&
#44400
0&
#44500
b111 %
1&
#44600
0&
#44700
b0 %
1&
#44800
0&
#44900
b1 %
1&
#45000
0&
#45100
b10 %
1&
#45200
0&
#45300
1$
b1111 +
1*
1#
b11 %
1&
#45400
0&
#45500
0#
b100 %
1&
#45600
0&
#45700
b101 %
1&
#45800
0&
#45900
b110 %
1&
#46000
0&
#46100
b111 %
1&
#46200
0&
#46300
b0 %
1&
#46400
0&
#46500
b1 %
1&
#46600
0&
#46700
b10 %
1&
#46800
0&
#46900
0*
1#
b11 %
1&
#47000
0&
#47100
0#
b100 %
1&
#47200
0&
#47300
b101 %
1&
#47400
0&
#47500
b110 %
1&
#47600
0&
#47700
b111 %
1&
#47800
0&
#47900
b0 %
1&
#48000
0&
#48100
b1 %
1&
#48200
0&
#48300
b10 %
1&
#48400
0&
#48500
0$
b0 +
1*
1#
b11 %
1&
#48600
0&
#48700
0#
b100 %
1&
#48800
0&
#48900
b101 %
1&
#49000
0&
#49100
b110 %
1&
#49200
0&
#49300
b111 %
1&
#49400
0&
#49500
b0 %
1&
#49600
0&
#49700
b1 %
1&
#49800
0&
#49900
b10 %
1&
#50000
0&
#50100
0*
1#
b11 %
1&
#50200
0&
#50300
0#
b100 %
1&
#50400
0&
#50500
b101 %
1&
#50600
0&
#50700
b110 %
1&
#50800
0&
#50900
b111 %
1&
#51000
0&
#51100
b0 %
1&
#51200
0&
#51300
b1 %
1&
#51400
0&
#51500
b10 %
1&
#51600
0&
#51700
b1 +
1*
1#
b11 %
1&
#51800
0&
#51900
0#
b100 %
1&
#52000
0&
#52100
b101 %
1&
#52200
0&
#52300
b110 %
1&
#52400
0&
#52500
b111 %
1&
#52600
0&
#52700
b0 %
1&
#52800
0&
#52900
b1 %
1&
#53000
0&
#53100
b10 %
1&
#53200
0&
#53300
0*
1#
b11 %
1&
#53400
0&
#53500
0#
b100 %
1&
#53600
0&
#53700
b101 %
1&
#53800
0&
#53900
b110 %
1&
#54000
0&
#54100
b111 %
1&
#54200
0&
#54300
b0 %
1&
#54400
0&
#54500
b1 %
1&
#54600
0&
#54700
b10 %
1&
#54800
0&
#54900
b10 +
1*
1#
b11 %
1&
#55000
0&
#55100
0#
b100 %
1&
#55200
0&
#55300
b101 %
1&
#55400
0&
#55500
b110 %
1&
#55600
0&
#55700
b111 %
1&
#55800
0&
#55900
b0 %
1&
#56000
0&
#56100
b1 %
1&
#56200
0&
#56300
b10 %
1&
#56400
0&
#56500
0*
1#
b11 %
1&
#56600
0&
#56700
0#
b100 %
1&
#56800
0&
#56900
b101 %
1&
#57000
0&
#57100
b110 %
1&
#57200
0&
#57300
b111 %
1&
#57400
0&
#57500
b0 %
1&
#57600
0&
#57700
b1 %
1&
#57800
0&
#57900
b10 %
1&
#58000
0&
#58100
b11 +
1*
1#
b11 %
1&
#58200
0&
#58300
0#
b100 %
1&
#58400
0&
#58500
b101 %
1&
#58600
0&
#58700
b110 %
1&
#58800
0&
#58900
b111 %
1&
#59000
0&
#59100
b0 %
1&
#59200
0&
#59300
b1 %
1&
#59400
0&
#59500
b10 %
1&
#59600
0&
#59700
0*
1#
b11 %
1&
#59800
0&
#59900
0#
b100 %
1&
#60000
0&
#60100
b101 %
1&
#60200
0&
#60300
b110 %
1&
#60400
0&
#60500
b111 %
1&
#60600
0&
#60700
b0 %
1&
#60800
0&
#60900
b1 %
1&
#61000
0&
#61100
b10 %
1&
#61200
0&
#61300
b100 +
1*
1#
b11 %
1&
#61400
0&
#61500
0#
b100 %
1&
#61600
0&
#61700
b101 %
1&
#61800
0&
#61900
b110 %
1&
#62000
0&
#62100
b111 %
1&
#62200
0&
#62300
b0 %
1&
#62400
0&
#62500
b1 %
1&
#62600
0&
#62700
b10 %
1&
#62800
0&
#62900
0*
1#
b11 %
1&
#63000
0&
#63100
0#
b100 %
1&
#63200
0&
#63300
b101 %
1&
#63400
0&
#63500
b110 %
1&
#63600
0&
#63700
b111 %
1&
#63800
0&
#63900
b0 %
1&
#64000
0&
#64100
b1 %
1&
#64200
0&
#64300
b10 %
1&
#64400
0&
#64500
b101 +
1*
1#
b11 %
1&
#64600
0&
#64700
0#
b100 %
1&
#64800
0&
#64900
b101 %
1&
#65000
0&
#65100
b110 %
1&
#65200
0&
#65300
b111 %
1&
#65400
0&
#65500
b0 %
1&
#65600
0&
#65700
b1 %
1&
#65800
0&
#65900
b10 %
1&
#66000
0&
#66100
0*
1#
b11 %
1&
#66200
0&
#66300
0#
b100 %
1&
#66400
0&
#66500
b101 %
1&
#66600
0&
#66700
b110 %
1&
#66800
0&
#66900
b111 %
1&
#67000
0&
#67100
b0 %
1&
#67200
0&
#67300
b1 %
1&
#67400
0&
#67500
b10 %
1&
#67600
0&
#67700
b110 +
1*
1#
b11 %
1&
#67800
0&
#67900
0#
b100 %
1&
#68000
0&
#68100
b101 %
1&
#68200
0&
#68300
b110 %
1&
#68400
0&
#68500
b111 %
1&
#68600
0&
#68700
b0 %
1&
#68800
0&
#68900
b1 %
1&
#69000
0&
#69100
b10 %
1&
#69200
0&
#69300
0*
1#
b11 %
1&
#69400
0&
#69500
0#
b100 %
1&
#69600
0&
#69700
b101 %
1&
#69800
0&
#69900
b110 %
1&
#70000
0&
1(
b11011010 '
b11011010 .
#70100
b11011010 3
14
b111 %
1&
#70200
0&
#70300
b0 %
16
1&
#70400
0&
0(
#70500
b1 %
1&
#70600
0&
#70700
b10 %
1&
#70800
0&
#70900
b111 +
1*
1#
b11 %
1&
#71000
0&
#71100
0#
b100 %
1&
#71200
0&
#71300
b101 %
1&
#71400
0&
#71500
b110 %
1&
#71600
0&
#71700
b111 %
1&
#71800
0&
#71900
b0 %
1&
#72000
0&
#72100
b1 %
1&
#72200
0&
#72300
b10 %
1&
#72400
0&
#72500
0*
1#
b11 %
1&
#72600
0&
#72700
0#
b100 %
1&
#72800
0&
#72900
b101 %
1&
#73000
0&
#73100
b110 %
1&
#73200
0&
#73300
b111 %
1&
#73400
0&
#73500
b0 %
1&
#73600
0&
#73700
b1 %
1&
#73800
0&
#73900
b10 %
1&
#74000
0&
#74100
b1000 +
1*
1#
b11 %
1&
#74200
0&
#74300
0#
b100 %
1&
#74400
0&
#74500
b101 %
1&
#74600
0&
#74700
b110 %
1&
#74800
0&
#74900
b111 %
1&
#75000
0&
#75100
b0 %
1&
#75200
0&
#75300
b1 %
1&
#75400
0&
#75500
b10 %
1&
#75600
0&
#75700
0*
1#
b11 %
1&
#75800
0&
#75900
0#
b100 %
1&
#76000
0&
#76100
b101 %
1&
#76200
0&
#76300
b110 %
1&
#76400
0&
#76500
b111 %
1&
#76600
0&
#76700
b0 %
1&
#76800
0&
#76900
b1 %
1&
#77000
0&
#77100
b10 %
1&
#77200
0&
#77300
b1001 +
1*
1#
b11 %
1&
#77400
0&
#77500
0#
b100 %
1&
#77600
0&
#77700
b101 %
1&
#77800
0&
#77900
b110 %
1&
#78000
0&
#78100
b111 %
1&
#78200
0&
#78300
b0 %
1&
#78400
0&
#78500
b1 %
1&
#78600
0&
#78700
b10 %
1&
#78800
0&
#78900
0*
1#
b11 %
1&
#79000
0&
#79100
0#
b100 %
1&
#79200
0&
#79300
b101 %
1&
#79400
0&
#79500
b110 %
1&
#79600
0&
#79700
b111 %
1&
#79800
0&
#79900
b0 %
1&
#80000
0&
#80100
b1 %
1&
#80200
0&
#80300
b10 %
1&
#80400
0&
1,
#80500
1/
b1010 +
b1 2
1*
0"
15
1#
b11 %
17
1:
1&
#80600
0&
#80700
0#
b100 %
18
1&
#80800
0&
#80900
b101 %
1&
#81000
0&
#81100
b110 %
1&
#81200
0&
#81300
b111 %
1&
#81400
0&
#81500
b0 %
1&
#81600
0&
#81700
b1 %
1&
#81800
0&
#81900
b10 %
1&
#82000
0&
#82100
0*
1#
b11 %
1&
#82200
0&
#82300
0#
b100 %
1&
#82400
0&
#82500
b101 %
1&
#82600
0&
#82700
b110 %
1&
#82800
0&
#82900
b111 %
1&
#83000
0&
#83100
b0 %
1&
#83200
0&
#83300
b1 %
1&
#83400
0&
#83500
b10 %
1&
#83600
0&
#83700
0/
b0 2
b1 1
0!
b1011 +
1*
1#
b11 %
1&
#83800
0&
#83900
0#
b100 %
1&
#84000
0&
#84100
b101 %
1&
#84200
0&
#84300
b110 %
1&
#84400
0&
#84500
b111 %
1&
#84600
0&
#84700
b0 %
1&
#84800
0&
#84900
b1 %
1&
#85000
0&
#85100
b10 %
1&
#85200
0&
#85300
0*
1#
b11 %
1&
#85400
0&
#85500
0#
b100 %
1&
#85600
0&
#85700
b101 %
1&
#85800
0&
#85900
b110 %
1&
#86000
0&
#86100
b111 %
1&
#86200
0&
#86300
b0 %
1&
#86400
0&
#86500
b1 %
1&
#86600
0&
#86700
b10 %
1&
#86800
0&
#86900
b1100 +
b1 2
1*
1#
b11 %
1&
#87000
0&
#87100
0#
b100 %
1&
#87200
0&
#87300
b101 %
1&
#87400
0&
#87500
b110 %
1&
#87600
0&
#87700
b111 %
1&
#87800
0&
#87900
b0 %
1&
#88000
0&
#88100
b1 %
1&
#88200
0&
#88300
b10 %
1&
#88400
0&
#88500
0*
1#
b11 %
1&
#88600
0&
#88700
0#
b100 %
1&
#88800
0&
#88900
b101 %
1&
#89000
0&
#89100
b110 %
1&
#89200
0&
#89300
b111 %
1&
#89400
0&
#89500
b0 %
1&
#89600
0&
#89700
b1 %
1&
#89800
0&
#89900
b10 %
1&
#90000
0&
#90100
b10 2
b1101 +
1*
1#
b11 %
1&
#90200
0&
#90300
0#
b100 %
1&
#90400
0&
#90500
b101 %
1&
#90600
0&
#90700
b110 %
1&
#90800
0&
#90900
b111 %
1&
#91000
0&
#91100
b0 %
1&
#91200
0&
#91300
b1 %
1&
#91400
0&
#91500
b10 %
1&
#91600
0&
#91700
0*
1#
b11 %
1&
#91800
0&
#91900
0#
b100 %
1&
#92000
0&
#92100
b101 %
1&
#92200
0&
#92300
b110 %
1&
#92400
0&
#92500
b111 %
1&
#92600
0&
#92700
b0 %
1&
#92800
0&
#92900
b1 %
1&
#93000
0&
#93100
b10 %
1&
#93200
0&
#93300
b1110 +
b11 2
1*
1#
b11 %
1&
#93400
0&
#93500
0#
b100 %
1&
#93600
0&
#93700
b101 %
1&
#93800
0&
#93900
b110 %
1&
#94000
0&
#94100
b111 %
1&
#94200
0&
#94300
b0 %
1&
#94400
0&
#94500
b1 %
1&
#94600
0&
#94700
b10 %
1&
#94800
0&
#94900
0*
1#
b11 %
1&
#95000
0&
#95100
0#
b100 %
1&
#95200
0&
#95300
b101 %
1&
#95400
0&
#95500
b110 %
1&
#95600
0&
#95700
b111 %
1&
#95800
0&
#95900
b0 %
1&
#96000
0&
#96100
b1 %
1&
#96200
0&
#96300
b10 %
1&
#96400
0&
#96500
b100 2
1$
b1111 +
1*
1#
b11 %
1&
#96600
0&
#96700
0#
b100 %
1&
#96800
0&
#96900
b101 %
1&
#97000
0&
#97100
b110 %
1&
#97200
0&
#97300
b111 %
1&
#97400
0&
#97500
b0 %
1&
#97600
0&
#97700
b1 %
1&
#97800
0&
#97900
b10 %
1&
#98000
0&
#98100
0*
1#
b11 %
1&
#98200
0&
#98300
0#
b100 %
1&
#98400
0&
#98500
b101 %
1&
#98600
0&
#98700
b110 %
1&
#98800
0&
#98900
b111 %
1&
#99000
0&
#99100
b0 %
1&
#99200
0&
#99300
b1 %
1&
#99400
0&
#99500
b10 %
1&
#99600
0&
#99700
0$
b0 +
b101 2
1*
1#
b11 %
1&
#99800
0&
#99900
0#
b100 %
1&
#100000
0&
#100100
b101 %
1&
#100200
0&
#100300
b110 %
1&
#100400
0&
#100500
b111 %
1&
#100600
0&
#100700
b0 %
1&
#100800
0&
#100900
b1 %
1&
#101000
0&
#101100
b10 %
1&
#101200
0&
#101300
0*
1#
b11 %
1&
#101400
0&
#101500
0#
b100 %
1&
#101600
0&
#101700
b101 %
1&
#101800
0&
#101900
b110 %
1&
#102000
0&
#102100
b111 %
1&
#102200
0&
#102300
b0 %
1&
#102400
0&
#102500
b1 %
1&
#102600
0&
#102700
b10 %
1&
#102800
0&
#102900
b110 2
b1 +
1*
1#
b11 %
1&
#103000
0&
#103100
0#
b100 %
1&
#103200
0&
#103300
b101 %
1&
#103400
0&
#103500
b110 %
1&
#103600
0&
#103700
b111 %
1&
#103800
0&
#103900
b0 %
1&
#104000
0&
#104100
b1 %
1&
#104200
0&
#104300
b10 %
1&
#104400
0&
#104500
0*
1#
b11 %
1&
#104600
0&
#104700
0#
b100 %
1&
#104800
0&
#104900
b101 %
1&
#105000
0&
#105100
b110 %
1&
#105200
0&
#105300
b111 %
1&
#105400
0&
#105500
b0 %
1&
#105600
0&
#105700
b1 %
1&
#105800
0&
#105900
b10 %
1&
#106000
0&
#106100
b10 +
b111 2
1*
1#
b11 %
1&
#106200
0&
#106300
0#
b100 %
1&
#106400
0&
#106500
b101 %
1&
#106600
0&
#106700
b110 %
1&
#106800
0&
#106900
b111 %
1&
#107000
0&
#107100
b0 %
1&
#107200
0&
#107300
b1 %
1&
#107400
0&
#107500
b10 %
1&
#107600
0&
#107700
0*
1#
b11 %
1&
#107800
0&
#107900
0#
b100 %
1&
#108000
0&
#108100
b101 %
1&
#108200
0&
#108300
b110 %
1&
#108400
0&
#108500
b111 %
1&
#108600
0&
#108700
b0 %
1&
#108800
0&
#108900
b1 %
1&
#109000
0&
#109100
b10 %
1&
#109200
0&
#109300
b1000 2
b11 +
1*
1#
b11 %
1&
#109400
0&
#109500
0#
b100 %
1&
#109600
0&
#109700
b101 %
1&
#109800
0&
#109900
b110 %
1&
#110000
0&
#110100
b111 %
1&
#110200
0&
#110300
b0 %
1&
#110400
0&
#110500
b1 %
1&
#110600
0&
#110700
b10 %
1&
#110800
0&
#110900
0*
1#
b11 %
1&
#111000
0&
#111100
0#
b100 %
1&
#111200
0&
#111300
b101 %
1&
#111400
0&
#111500
b110 %
1&
#111600
0&
#111700
b111 %
1&
#111800
0&
#111900
b0 %
1&
#112000
0&
#112100
b1 %
1&
#112200
0&
#112300
b10 %
1&
#112400
0&
#112500
b100 +
b1001 2
1*
1#
b11 %
1&
#112600
0&
#112700
0#
b100 %
1&
#112800
0&
#112900
b101 %
1&
#113000
0&
#113100
b110 %
1&
#113200
0&
#113300
b111 %
1&
#113400
0&
#113500
b0 %
1&
#113600
0&
#113700
b1 %
1&
#113800
0&
#113900
b10 %
1&
#114000
0&
#114100
0*
1#
b11 %
1&
#114200
0&
#114300
0#
b100 %
1&
#114400
0&
#114500
b101 %
1&
#114600
0&
#114700
b110 %
1&
#114800
0&
#114900
b111 %
1&
#115000
0&
#115100
b0 %
1&
#115200
0&
#115300
b1 %
1&
#115400
0&
#115500
b10 %
1&
#115600
0&
#115700
b1010 2
b101 +
1*
1#
b11 %
1&
#115800
0&
