D_Flip_Flop.v
module D_Flip_Flop(Q, D, Clk, rst);
    input D;
    input Clk;
    output reg Q;
    input rst;

    initial Q = 0;

    always @ (posedge Clk) begin
        if(rst == 1'b1)
            Q <= 1'b0;
        else
            Q <= D;
    end
endmodule

checksum.v
`include "D_Flip_Flop.v"
`default_nettype none

module checksum(
    input [39:0]data_i,
    input       we_i,
                clk_i,
                rst_i, 

    input [16:0] mask_i,

    output reg [15:0] out_o,
    output reg out_valid_o
);

    initial out_o = 0;
    initial out_valid_o = 0;
    
    reg [39:0] data = 0;
    reg [5:0] count = 0;
    reg valid = 0;

    wire rst_ff = !valid;

    wire serial_data = data[39];
    // data
    always @ (posedge clk_i)begin
        if(rst_i)
            data <= 0;
        else if (we_i)
            data <= data_i;
    end

    // valid
    always @ (posedge clk_i)begin
        if(rst_i)
            valid <= 0;
        else if (we_i)
            valid <= 1;
        else if (count == 41)
            valid <= 0;
    end

    // count
    always @ (posedge clk_i)begin
        if(rst_i | we_i)
            count <= 0;
        else if (we_i)
            count <= 1;
        else if(count == 41)
            count <= 0;
        else if(valid)
            count <= count+1;
    end
    
    // right shift each cycle
    always @ (posedge clk_i)begin
        if(valid & !we_i)begin
            data <= data << 1;
        end
     
    end

    wire done = count == 41;

    //out_o
    always @ (posedge clk_i)begin
        if(rst_i | we_i)
            out_o <= 0;
        else if(done)
            out_o <= Q;
    end

    //out_valid_o
    always @ (posedge clk_i)begin
        if(rst_i | we_i)
            out_valid_o <= 0;
        else if(done)
            out_valid_o <= 1;
    end
    



    wire [15:0]     D,
                    Q,
                    xout;

    wire            invert_en = Q[15];

    wire [15:0] invert = {16{invert_en}} & mask_i[15:0];


    assign xout[0] =  invert[0] ^ serial_data;
    assign xout[15:1] = invert[15:1] ^ Q[14:0];

    D_Flip_Flop d0(Q[0], xout[0], clk_i, rst_ff);
    D_Flip_Flop d1(Q[1], xout[1], clk_i, rst_ff);
    D_Flip_Flop d2(Q[2], xout[2], clk_i, rst_ff);
    D_Flip_Flop d3(Q[3], xout[3], clk_i, rst_ff);
    D_Flip_Flop d4(Q[4], xout[4], clk_i, rst_ff);
    D_Flip_Flop d5(Q[5], xout[5], clk_i, rst_ff);
    D_Flip_Flop d6(Q[6], xout[6], clk_i, rst_ff);
    D_Flip_Flop d7(Q[7], xout[7], clk_i, rst_ff);
    D_Flip_Flop d8(Q[8], xout[8], clk_i, rst_ff);
    D_Flip_Flop d9(Q[9], xout[9], clk_i, rst_ff);
    D_Flip_Flop d10(Q[10], xout[10], clk_i, rst_ff);
    D_Flip_Flop d11(Q[11], xout[11], clk_i, rst_ff);
    D_Flip_Flop d12(Q[12], xout[12], clk_i, rst_ff);
    D_Flip_Flop d13(Q[13], xout[13], clk_i, rst_ff);
    D_Flip_Flop d14(Q[14], xout[14], clk_i, rst_ff);
    D_Flip_Flop d15(Q[15], xout[15], clk_i, rst_ff);
endmodule

Tb_chksum.v
`timescale 1ns/10ps

`default_nettype none

`include "checksum.v"

module Top;
    
    reg [39:0] data_i;
    reg       we_i,
                clk_i=0,
                rst_i; 

    reg [16:0] mask_i;

    wire [15:0] out_o;
    wire out_valid_o;
    
    checksum ck(
        data_i,
        we_i,
        clk_i,
        rst_i, 

        mask_i,

        out_o,
        out_valid_o
    );


    initial begin
        $dumpfile("out.vcd");
        $dumpvars(0, Top);

        mask_i = 17'b10001000000100001;
        rst_i=0;
        data_i = {"Hi!", 16'b0011000111111101};
        we_i=0; #2;
        we_i = 1;#2;
        we_i=0; #200;

        data_i = "Hi!\0\0";
        we_i=0; #2;
        we_i = 1;#2;
        we_i=0; #100;
        $finish();

        
        
    end
    // master clk
    always begin
        #1;
        clk_i <= ~clk_i;
    end
    
endmodule

out.vcd
$date
	Wed Mar 31 14:44:47 2021
$end
$version
	Icarus Verilog
$end
$timescale
	10ps
$end
$scope module Top $end
$var wire 1 ! out_valid_o $end
$var wire 16 " out_o [15:0] $end
$var reg 1 # clk_i $end
$var reg 40 $ data_i [39:0] $end
$var reg 17 % mask_i [16:0] $end
$var reg 1 & rst_i $end
$var reg 1 ' we_i $end
$scope module ck $end
$var wire 1 # clk_i $end
$var wire 40 ( data_i [39:0] $end
$var wire 16 ) invert [15:0] $end
$var wire 17 * mask_i [16:0] $end
$var wire 1 & rst_i $end
$var wire 1 ' we_i $end
$var wire 16 + xout [15:0] $end
$var wire 1 , serial_data $end
$var wire 1 - rst_ff $end
$var wire 1 . invert_en $end
$var wire 1 / done $end
$var wire 16 0 Q [15:0] $end
$var reg 6 1 count [5:0] $end
$var reg 40 2 data [39:0] $end
$var reg 16 3 out_o [15:0] $end
$var reg 1 ! out_valid_o $end
$var reg 1 4 valid $end
$scope module d0 $end
$var wire 1 # Clk $end
$var wire 1 5 D $end
$var wire 1 - rst $end
$var reg 1 6 Q $end
$upscope $end
$scope module d1 $end
$var wire 1 # Clk $end
$var wire 1 7 D $end
$var wire 1 - rst $end
$var reg 1 8 Q $end
$upscope $end
$scope module d10 $end
$var wire 1 # Clk $end
$var wire 1 9 D $end
$var wire 1 - rst $end
$var reg 1 : Q $end
$upscope $end
$scope module d11 $end
$var wire 1 # Clk $end
$var wire 1 ; D $end
$var wire 1 - rst $end
$var reg 1 < Q $end
$upscope $end
$scope module d12 $end
$var wire 1 # Clk $end
$var wire 1 = D $end
$var wire 1 - rst $end
$var reg 1 > Q $end
$upscope $end
$scope module d13 $end
$var wire 1 # Clk $end
$var wire 1 ? D $end
$var wire 1 - rst $end
$var reg 1 @ Q $end
$upscope $end
$scope module d14 $end
$var wire 1 # Clk $end
$var wire 1 A D $end
$var wire 1 - rst $end
$var reg 1 B Q $end
$upscope $end
$scope module d15 $end
$var wire 1 # Clk $end
$var wire 1 C D $end
$var wire 1 - rst $end
$var reg 1 D Q $end
$upscope $end
$scope module d2 $end
$var wire 1 # Clk $end
$var wire 1 E D $end
$var wire 1 - rst $end
$var reg 1 F Q $end
$upscope $end
$scope module d3 $end
$var wire 1 # Clk $end
$var wire 1 G D $end
$var wire 1 - rst $end
$var reg 1 H Q $end
$upscope $end
$scope module d4 $end
$var wire 1 # Clk $end
$var wire 1 I D $end
$var wire 1 - rst $end
$var reg 1 J Q $end
$upscope $end
$scope module d5 $end
$var wire 1 # Clk $end
$var wire 1 K D $end
$var wire 1 - rst $end
$var reg 1 L Q $end
$upscope $end
$scope module d6 $end
$var wire 1 # Clk $end
$var wire 1 M D $end
$var wire 1 - rst $end
$var reg 1 N Q $end
$upscope $end
$scope module d7 $end
$var wire 1 # Clk $end
$var wire 1 O D $end
$var wire 1 - rst $end
$var reg 1 P Q $end
$upscope $end
$scope module d8 $end
$var wire 1 # Clk $end
$var wire 1 Q D $end
$var wire 1 - rst $end
$var reg 1 R Q $end
$upscope $end
$scope module d9 $end
$var wire 1 # Clk $end
$var wire 1 S D $end
$var wire 1 - rst $end
$var reg 1 T Q $end
$upscope $end
$upscope $end
$upscope $end
$enddefinitions $end
#0
$dumpvars
0T
0S
0R
0Q
0P
0O
0N
0M
0L
0K
0J
0I
0H
0G
0F
0E
0D
0C
0B
0A
0@
0?
0>
0=
0<
0;
0:
09
08
07
06
05
04
b0 3
b0 2
b0 1
b0 0
0/
0.
1-
0,
b0 +
b10001000000100001 *
b0 )
b100100001101001001000010011000111111101 (
0'
0&
b10001000000100001 %
b100100001101001001000010011000111111101 $
0#
b0 "
0!
$end
#100
1#
#200
0#
1'
#300
b1 1
0-
14
b100100001101001001000010011000111111101 2
1#
#400
0#
0'
#500
15
b1 +
1,
b10 1
b1001000011010010010000100110001111111010 2
1#
#600
0#
#700
05
17
b10 +
0,
b10000110100100100001001100011111110100 2
b11 1
b1 0
16
1#
#800
0#
#900
07
1E
b100 +
06
b10 0
18
b100 1
b100001101001001000010011000111111101000 2
1#
#1000
0#
#1100
15
0E
1G
b1001 +
1,
b1000011010010010000100110001111111010000 2
b101 1
1F
b100 0
08
1#
#1200
0#
#1300
17
0G
1I
05
b10010 +
0,
16
0F
b1001 0
1H
b110 1
b110100100100001001100011111110100000 2
1#
#1400
0#
#1500
07
1E
0I
1K
b100100 +
b1101001001000010011000111111101000000 2
b111 1
1J
0H
18
b10010 0
06
1#
#1600
0#
#1700
0E
1G
0K
1M
b1001000 +
08
1F
0J
b100100 0
1L
b1000 1
b11010010010000100110001111111010000000 2
1#
#1800
0#
#1900
0G
1I
0M
1O
b10010000 +
b110100100100001001100011111110100000000 2
b1001 1
1N
0L
1H
b1001000 0
0F
1#
#2000
0#
#2100
0I
1K
0O
1Q
15
b100100001 +
1,
0H
1J
0N
b10010000 0
1P
b1010 1
b1101001001000010011000111111101000000000 2
1#
#2200
0#
#2300
17
0K
1M
0Q
1S
b1001000011 +
b1010010010000100110001111111010000000000 2
b1011 1
1R
0P
1L
0J
b100100001 0
16
1#
#2400
0#
#2500
1E
0M
1O
0S
19
05
b10010000110 +
0,
18
0L
1N
0R
b1001000011 0
1T
b1100 1
b100100100001001100011111110100000000000 2
1#
#2600
0#
#2700
15
07
1G
0O
1Q
09
1;
b100100001101 +
1,
b1001001000010011000111111101000000000000 2
b1101 1
1:
0T
1P
0N
1F
b10010000110 0
06
1#
#2800
0#
#2900
17
0E
1I
0Q
1S
0;
1=
05
b1001000011010 +
0,
16
08
1H
0P
1R
0:
b100100001101 0
1<
b1110 1
b10010000100110001111111010000000000000 2
1#
#3000
0#
#3100
07
1E
0G
1K
0S
19
0=
1?
b10010000110100 +
b100100001001100011111110100000000000000 2
b1111 1
1>
0<
1T
0R
1J
0F
18
b1001000011010 0
06
1#
#3200
0#
#3300
0E
1G
0I
1M
09
1;
0?
1A
15
b100100001101001 +
1,
08
1F
0H
1L
0T
1:
0>
b10010000110100 0
1@
b10000 1
b1001000010011000111111101000000000000000 2
1#
#3400
0#
#3500
05
17
0G
1I
0K
1O
0;
1=
0A
1C
b1001000011010010 +
0,
b10000100110001111111010000000000000000 2
b10001 1
1B
0@
1<
0:
1N
0J
1H
0F
b100100001101001 0
16
1#
#3600
0#
#3700
15
07
1E
0I
0K
0M
1Q
1=
1?
0C
b11000110000101 +
b1000000100001 )
1.
06
18
0H
1J
0L
1P
0<
1>
0B
b1001000011010010 0
1D
b10010 1
b100001001100011111110100000000000000000 2
1#
#3800
0#
#3900
0=
15
17
0E
1G
0K
0O
1S
1A
b0 )
b110001100001011 +
1,
0.
b1000010011000111111101000000000000000000 2
b10011 1
0D
1@
1R
0N
0J
1F
08
b11000110000101 0
16
1#
#4000
0#
#4100
1E
0G
1I
0Q
19
0?
1C
05
b1100011000010110 +
0,
18
0F
1H
0P
1T
0>
b110001100001011 0
1B
b10100 1
b100110001111111010000000000000000000 2
1#
#4200
0#
#4300
15
1=
07
1G
0I
0K
0S
1;
0A
b1000000100001 )
b1001110000001101 +
1.
b1001100011111110100000000000000000000 2
b10101 1
1D
0@
1:
0R
1J
0H
1F
b1100011000010110 0
06
1#
#4400
0#
#4500
17
0E
1I
1K
09
0=
1?
0C
b10100000111011 +
16
08
1H
0J
0T
1<
1>
b1001110000001101 0
0B
b10110 1
b10011000111111101000000000000000000000 2
1#
#4600
0#
#4700
05
1=
1E
0G
1K
1M
0;
0?
1A
b0 )
b101000001110110 +
0.
b100110001111111010000000000000000000000 2
b10111 1
0D
1@
0>
0:
1L
1J
0F
b10100000111011 0
18
1#
#4800
0#
#4900
07
1G
0I
1O
0=
1?
0A
1C
15
b1010000011101101 +
1,
06
1F
0H
1N
0<
1>
0@
b101000001110110 0
1B
b11000 1
b1001100011111110100000000000000000000000 2
1#
#5000
0#
#5100
1=
15
17
0E
1I
1K
1Q
0?
1A
0C
b1000000100001 )
b101000111111011 +
0,
1.
b11000111111101000000000000000000000000 2
b11001 1
1D
0B
1@
0>
1P
0J
1H
08
b1010000011101101 0
16
1#
#5200
0#
#5300
05
0=
1E
0G
1K
1S
1?
0A
1C
b1010001111110110 +
b0 )
0.
18
0F
1J
1R
1>
0@
1B
b101000111111011 0
0D
b11010 1
b110001111111010000000000000000000000000 2
1#
#5400
0#
#5500
0K
1=
05
07
1G
0I
19
0?
1A
0C
b1000000100001 )
b101011111001100 +
1,
1.
b1100011111110100000000000000000000000000 2
b11011 1
1D
0B
1@
0>
1T
0H
1F
b1010001111110110 0
06
1#
#5600
0#
#5700
15
0=
0E
1I
0K
0M
1;
1?
0A
1C
b1010111110011001 +
b0 )
0.
08
1H
0J
0L
1:
1>
0@
1B
b101011111001100 0
0D
b11100 1
b1000111111101000000000000000000000000000 2
1#
#5800
0#
#5900
15
17
0G
0K
0O
0=
0?
1A
0C
b1000000100001 )
b100111100010011 +
0,
1.
b1111111010000000000000000000000000000 2
b11101 1
1D
0B
1@
0>
1<
0N
1J
0F
b1010111110011001 0
16
1#
#6000
0#
#6100
05
1K
1=
1E
0I
0Q
0A
1C
b1001111000100110 +
b0 )
0.
18
0H
0P
0@
1B
b100111100010011 0
0D
b11110 1
b11111110100000000000000000000000000000 2
1#
#6200
0#
#6300
15
0=
07
1G
1K
1M
0S
1?
0C
b1000000100001 )
b10110001101101 +
1.
b111111101000000000000000000000000000000 2
b11111 1
1D
0B
1>
0R
1L
0J
1F
b1001111000100110 0
06
1#
#6400
0#
#6500
0K
1=
17
0E
1I
1O
09
0?
1A
15
b0 )
b101100011011011 +
0.
1,
16
08
1H
1N
0T
0>
1@
b10110001101101 0
0D
b100000 1
b1111111010000000000000000000000000000000 2
1#
#6600
0#
#6700
1E
0G
1K
0M
1Q
0;
1?
0A
1C
b1011000110110111 +
b1111110100000000000000000000000000000000 2
b100001 1
1B
0@
1>
0:
1P
0L
1J
0F
b101100011011011 0
18
1#
#6800
0#
#6900
05
0K
1G
0I
1M
0O
1S
1=
1A
0C
b111001101001110 +
b1000000100001 )
1.
1F
0H
1L
0N
1R
0<
1@
0B
b1011000110110111 0
1D
b100010 1
b1111101000000000000000000000000000000000 2
1#
#7000
0#
#7100
15
0=
07
1I
0K
0M
1O
0Q
19
1C
b0 )
b1110011010011101 +
0.
b1111010000000000000000000000000000000000 2
b100011 1
0D
1B
1T
0P
1N
0L
0J
1H
b111001101001110 0
06
1#
#7200
0#
#7300
05
1=
17
0E
0K
0O
1Q
0S
1;
0?
b1101110100011010 +
b1000000100001 )
1.
16
08
1J
0N
1P
0R
1:
0>
b1110011010011101 0
1D
b100100 1
b1110100000000000000000000000000000000000 2
1#
#7400
0#
#7500
07
1E
0G
0Q
1S
09
0=
1?
0A
b1010101000010100 +
b1101000000000000000000000000000000000000 2
b100101 1
0@
1>
1<
0T
1R
0P
0F
18
b1101110100011010 0
06
1#
#7600
0#
#7700
0E
1G
0I
0S
19
0;
0?
1A
0C
b100010000001000 +
08
1F
0H
0R
1T
0:
0>
1@
b1010101000010100 0
0B
b100110 1
b1010000000000000000000000000000000000000 2
1#
#7800
0#
#7900
05
0G
1I
0K
09
1;
0=
0A
1C
b0 )
b1000100000010000 +
0,
0.
b100000000000000000000000000000000000000 2
b100111 1
0D
1B
0@
0<
1:
0T
0J
1H
b100010000001000 0
0F
1#
#8000
0#
#8100
0I
0K
0;
0=
0C
05
b1000000100001 )
b0 +
1.
1,
0H
1J
0:
1<
0B
b1000100000010000 0
1D
b101000 1
b1000000000000000000000000000000000000000 2
1#
#8200
0#
#8300
05
0K
0=
b0 )
b0 +
0,
0.
b0 2
1/
b101001 1
0D
0<
b0 0
0J
1#
#8400
0#
#8500
1-
04
0/
b0 1
1!
1#
