D_Flip_Flop.v
module D_Flip_Flop(Q, D, Clk, rst);
    input D;
    input Clk;
    output reg Q;
    input rst;

    initial Q = 0;

    always @ (posedge Clk) begin
        if(rst == 1'b1)
            Q <= 1'b0;
        else
            Q <= D;
    end
endmodule

checksum.v
`include "D_Flip_Flop.v"
`default_nettype none

module checksum(
    input [39:0]data_i,
    input       we_i,
                clk_i,
                rst_i, 

    input [16:0] mask_i,

    output reg [15:0] out_o,
    output reg out_valid_o
);

    initial out_o = 0;
    initial out_valid_o = 0;
    
    reg [39:0] data = 0;
    reg [5:0] count = 0;
    reg valid = 0;

    wire rst_ff = !valid;

    wire serial_data = data[39];
    // data
    always @ (posedge clk_i)begin
        if(rst_i)
            data <= 0;
        else if (we_i)
            data <= data_i;
    end

    // valid
    always @ (posedge clk_i)begin
        if(rst_i)
            valid <= 0;
        else if (we_i)
            valid <= 1;
        else if (count == 41)
            valid <= 0;
    end

    // count
    always @ (posedge clk_i)begin
        if(rst_i | we_i)
            count <= 0;
        else if (we_i)
            count <= 1;
        else if(count == 41)
            count <= 0;
        else if(valid)
            count <= count+1;
    end
    
    // right shift each cycle
    always @ (posedge clk_i)begin
        if(valid & !we_i)begin
            data <= data << 1;
        end
     
    end

    wire done = count == 41;

    //out_o
    always @ (posedge clk_i)begin
        if(rst_i | we_i)
            out_o <= 0;
        else if(done)
            out_o <= Q;
    end

    //out_valid_o
    always @ (posedge clk_i)begin
        if(rst_i | we_i)
            out_valid_o <= 0;
        else if(done)
            out_valid_o <= 1;
    end
    



    wire [15:0]     D,
                    Q,
                    xout;

    wire            invert_en = Q[15];

    wire [15:0] invert = {16{invert_en}} & mask_i[15:0];


    assign xout[0] =  invert[0] ^ serial_data;
    assign xout[15:1] = invert[15:1] ^ Q[14:0];

    D_Flip_Flop d0(Q[0], xout[0], clk_i, rst_ff);
    D_Flip_Flop d1(Q[1], xout[1], clk_i, rst_ff);
    D_Flip_Flop d2(Q[2], xout[2], clk_i, rst_ff);
    D_Flip_Flop d3(Q[3], xout[3], clk_i, rst_ff);
    D_Flip_Flop d4(Q[4], xout[4], clk_i, rst_ff);
    D_Flip_Flop d5(Q[5], xout[5], clk_i, rst_ff);
    D_Flip_Flop d6(Q[6], xout[6], clk_i, rst_ff);
    D_Flip_Flop d7(Q[7], xout[7], clk_i, rst_ff);
    D_Flip_Flop d8(Q[8], xout[8], clk_i, rst_ff);
    D_Flip_Flop d9(Q[9], xout[9], clk_i, rst_ff);
    D_Flip_Flop d10(Q[10], xout[10], clk_i, rst_ff);
    D_Flip_Flop d11(Q[11], xout[11], clk_i, rst_ff);
    D_Flip_Flop d12(Q[12], xout[12], clk_i, rst_ff);
    D_Flip_Flop d13(Q[13], xout[13], clk_i, rst_ff);
    D_Flip_Flop d14(Q[14], xout[14], clk_i, rst_ff);
    D_Flip_Flop d15(Q[15], xout[15], clk_i, rst_ff);
endmodule

rtl/UART_RX.v
module UART_RX#(parameter N = 8)                            // N = packet size
    (
    /* PORTLIST */
    output reg [N-1:0]  data_o,
    output              rx_done,
                        stop_bit,

    
    input               rx_i,
                        rx_en_i,
                        tick_i, 
                        clk_i,
                        rst_i
    );

    parameter   IDLE    = 0,
                READING = 1; 
        
    initial     data_o  = 0;


    // Internal registers
    reg state   = IDLE;

    assign rx_done = ~state;

    /////////////////////// STATE Machine //////////////////////
    /*
        Controls state transitions
    */
    always @ (posedge clk_i) begin
        if(rst_i)
            state <= IDLE;
        else
            state <= next(rx_i, state, rx_en_i, stop_bit_cond);
    end

    /*
        Next state decision (combinational logic)
    */
    function next;
        input rx_i;
        input state;
        input rx_en_i;
        input stop_bit_cond;
        
        begin
            case(state)
                IDLE:       if(!rx_i & rx_en_i)     next = READING;     // first neg-edge
                            else                    next = IDLE;
                
                READING:    if(stop_bit_cond)       next = IDLE;
                            else                    next = READING;

                default:                            next = IDLE;
            endcase
        end
    endfunction 

    reg [3:0]           counter     = 0;
    reg [$clog2(N):0]    bitcount    = 0;

    /*
        rx_i        |``````````\......../````````\................/`````````\................/````````````````````````````````
                    |      |        |        |        |        |        |        |        |        |        |        |        |
                                start bit    D7       D6       D5       D4       D3       D2       D1       D0    stop bit
        
        bitcount    <      0        ><   1   ><   2   ><   3   ><   4   ><    5  ><   6   ><   7   ><   8   ><   9   ><   0   ><
    */

    wire start_bit_cond     = (counter == 7)    &   (bitcount == 0);
    wire data_bit_cond      = (counter == 15)   &   (bitcount <= N);
    wire stop_bit_cond      = (counter == 15)   &   (bitcount == N+1)    &    (rx_i);   

    assign stop_bit = stop_bit_cond;

    // counter
    always @ (posedge tick_i)begin
        if(state == READING) begin
            if(start_bit_cond | data_bit_cond)
                counter <= 0;

            else 
                counter <= counter +1;
        end
        if(stop_bit_cond)
                counter <= 0;        
    end

    // bitcount
    always @ (posedge tick_i)begin
        if(state == READING)begin
            if(start_bit_cond | data_bit_cond)
                bitcount <= bitcount+1;            
            
        end
        if(stop_bit_cond)
                bitcount <= 0;
    end

    // data_o
    always @ (posedge tick_i)begin
        if(state == READING)begin
            if(start_bit_cond)
                data_o <= 0;
            if(data_bit_cond)
                data_o <=  {data_o[6:0], rx_i};  //SAMPLING
        end
    end
    
endmodule

CRC_Rx_Engine.v

`define MASK 17'b10001000000100001
module CRC_Rx_Engine
(
    input   rx_i, 
            rx_en_i,
            clk_i,
            tick_i,
            rst_i,

    output reg [23:0] out_o = 0, 
    output reg done_o = 0,
    output reg error_o = 0
);
    wire [7:0]  RX_data;
    wire        RX_done, 
                RX_stop_bit; 

    // Instantiate Rx module
    UART_RX#(.N(8)) RX
    (
        .data_o(RX_data),
        .rx_done(RX_done),
        .stop_bit(RX_stop_bit),

        .rx_i(rx_i),
        .rx_en_i(rx_en_i),
        .tick_i(tick_i), 
        .clk_i(clk_i),
        .rst_i(rst_i)
    );


    wire [39:0] chk_din;
    wire chk_we, chk_out_valid;
    wire [15:0] checksum_out;

    checksum chk(
        .data_i(chk_din),
        .we_i(chk_we),
        .clk_i(clk_i),
        .rst_i(rst_i), 

        .mask_i(`MASK),

        .out_o(checksum_out),
        .out_valid_o(chk_out_valid)
    );


    reg [4:0] state = 0;

    /* 
        Byte counter, Counts 0 - 4
        0, 1, 2     -   message bytes
        3, 4        -   checksum bytes
    */
    reg [2:0] bytecount = 0;

    //byte count
    always @ (posedge tick_i) begin
        if(rst_i) begin
            bytecount <= 0;
            rx_data_reg_valid <= 0;
        end

        else if(bytecount == 5) begin
            bytecount <= 0;
            rx_data_reg_valid <= 1;
        end

        else if(RX_stop_bit)
            bytecount <= bytecount+1;
    end

    wire [7:0] RX_data_reversed = {RX_data[0], RX_data[1], RX_data[2], RX_data[3], RX_data[4], RX_data[5], RX_data[6], RX_data[7]} ;

    reg [39:0] rx_data_reg = 0;
    reg rx_data_reg_valid = 0;

    // rx_data_reg
    always @ (posedge tick_i) begin
        if(rst_i)   
            rx_data_reg <= 0;

        else if(RX_stop_bit)
            rx_data_reg <= {RX_data_reversed, rx_data_reg[39:8]};
    end


    // state
    always @ (posedge tick_i) begin
        if(rst_i)begin
            state <= 0;
            out_o <= 0;
            done_o <= 0;
        end

        else if((state == 0) && rx_data_reg_valid) begin
            rx_data_reg_valid <= 0;
            out_o <= 0;
            done_o <= 0;
            state <= 1;
        end

        // generate checksum
        else if(state == 1) begin
            state <= 2;
        end

        else if((state == 2) & chk_out_valid) begin
            if(checksum_out == 0)
               error_o <= 0;
            else
                error_o <= 1;

            out_o <= rx_data_reg[39:16];
            done_o <= 1;
            state <= 0;
        end

    end

    assign chk_din = (state == 1) ? rx_data_reg : 0;
    assign chk_we = (state == 1);

endmodule

Top.v
`timescale 1ns/10ps

`default_nettype none

`include "rtl/UART_RX.v"
`include "CRC_Rx_Engine.v"
`include "checksum.v"

module Top;
    reg clk_master;
    reg tick;
    
    wire chng;
    
    reg [3:0] tick_counter;
    reg rx_i;
    
    wire [23:0] data_o;
    wire error;
    wire rx_done;
    reg rx_en = 1;

    wire rst_i = 0;

        
    CRC_Rx_Engine crc_rx
    (
        .rx_i(rx_i), 
        .rx_en_i(rx_en),
        .clk_i(clk_master),
        .tick_i(tick),
        .rst_i(rst_i),

        .out_o(data_o), 
        .error_o(error)
    );

    initial begin
        clk_master = 0;tick = 0; rx_en = 1;
        tick_counter = 0; rx_i = 1;
        $dumpfile("out_crc_rx.vcd");
        $dumpvars(0, Top);
        #60000;
        $finish();
    end

    
    reg [7:0] ct = 0;
    always @(posedge chng) begin
        ct <= ct+1;
    end

    reg [39:0] data = {"Hi!", 16'b0011000111111101};
    reg [7:0] i = 0;

    always @(posedge chng) begin
        
        case(ct)

        // PACKET 1
        2: rx_i <= 0;

        3: begin rx_i  <= data[i]; i <= i+1; end
        4: begin rx_i  <= data[i]; i <= i+1; end
        5: begin rx_i  <= data[i]; i <= i+1; end
        6: begin rx_i  <= data[i]; i <= i+1; end
        7: begin rx_i  <= data[i]; i <= i+1; end
        8: begin rx_i  <= data[i]; i <= i+1; end
        9: begin rx_i  <= data[i]; i <= i+1; end
        10: begin rx_i  <= data[i]; i <= i+1; end


        // PACKET 2
        16: rx_i <= 0;

        17:begin rx_i  <= data[i]; i <= i+1; end
        18:begin rx_i  <= data[i]; i <= i+1; end
        19:begin rx_i  <= data[i]; i <= i+1; end
        20:begin rx_i  <= data[i]; i <= i+1; end
        21:begin rx_i  <= data[i]; i <= i+1; end
        22:begin rx_i  <= data[i]; i <= i+1; end
        23:begin rx_i  <= data[i]; i <= i+1; end
        24:begin rx_i  <= data[i]; i <= i+1; end

        // PACKET 3
        29: rx_i<=0;

        30:begin rx_i  <= data[i]; i <= i+1; end
        31:begin rx_i  <= data[i]; i <= i+1; end
        32:begin rx_i  <= data[i]; i <= i+1; end
        33:begin rx_i  <= data[i]; i <= i+1; end
        34:begin rx_i  <= data[i]; i <= i+1; end
        35:begin rx_i  <= data[i]; i <= i+1; end
        36:begin rx_i  <= data[i]; i <= i+1; end
        37:begin rx_i  <= data[i]; i <= i+1; end

        // PACKET 4 (CHECKSUM)
        45: rx_i<=0;

        46:begin rx_i  <= data[i]; i <= i+1; end
        47:begin rx_i  <= data[i]; i <= i+1; end
        48:begin rx_i  <= data[i]; i <= i+1; end
        49:begin rx_i  <= data[i]; i <= i+1; end
        50:begin rx_i  <= data[i]; i <= i+1; end
        51:begin rx_i  <= data[i]; i <= i+1; end
        52:begin rx_i  <= data[i]; i <= i+1; end
        53:begin rx_i  <= data[i]; i <= i+1; end

        // PACKET 5 (CHECKSUM)
        59: rx_i<=0;

        60:begin rx_i  <= data[i]; i <= i+1; end
        61:begin rx_i  <= data[i]; i <= i+1; end
        62:begin rx_i  <= data[i]; i <= i+1; end
        63:begin rx_i  <= data[i]; i <= i+1; end
        64:begin rx_i  <= data[i]; i <= i+1; end
        65:begin rx_i  <= data[i]; i <= i+1; end
        66:begin rx_i  <= data[i]; i <= i+1; end
        67:begin rx_i  <= data[i]; i <= i+1; end

        default: rx_i<=1;

    endcase
    end








    // change
    always@(posedge tick) begin
        tick_counter <= tick_counter+1;
    end

    assign chng = (tick_counter == 15);

    
    
    
    // tick
    reg [2:0] clk_counter = 0;

    always@(posedge clk_master) begin
        clk_counter <= clk_counter+1;
    end
    wire ctr_chng = (clk_counter == 3);

    always@(posedge ctr_chng) begin
        tick <= ~tick;
    end



    // master clk
    always begin
        #1;
        clk_master <= ~clk_master;
    end
    
endmodule

out_crc_rx.vcd
$date
	Wed Mar 31 20:42:47 2021
$end
$version
	Icarus Verilog
$end
$timescale
	10ps
$end
$scope module Top $end
$var wire 1 ! rst_i $end
$var wire 1 " error $end
$var wire 24 # data_o [23:0] $end
$var wire 1 $ ctr_chng $end
$var wire 1 % chng $end
$var reg 3 & clk_counter [2:0] $end
$var reg 1 ' clk_master $end
$var reg 8 ( ct [7:0] $end
$var reg 40 ) data [39:0] $end
$var reg 8 * i [7:0] $end
$var reg 1 + rx_en $end
$var reg 1 , rx_i $end
$var reg 1 - tick $end
$var reg 4 . tick_counter [3:0] $end
$scope module crc_rx $end
$var wire 1 ' clk_i $end
$var wire 1 ! rst_i $end
$var wire 1 + rx_en_i $end
$var wire 1 , rx_i $end
$var wire 1 - tick_i $end
$var wire 1 / chk_we $end
$var wire 1 0 chk_out_valid $end
$var wire 40 1 chk_din [39:0] $end
$var wire 16 2 checksum_out [15:0] $end
$var wire 1 3 RX_stop_bit $end
$var wire 1 4 RX_done $end
$var wire 8 5 RX_data_reversed [7:0] $end
$var wire 8 6 RX_data [7:0] $end
$var reg 3 7 bytecount [2:0] $end
$var reg 1 8 done_o $end
$var reg 1 " error_o $end
$var reg 24 9 out_o [23:0] $end
$var reg 40 : rx_data_reg [39:0] $end
$var reg 1 ; rx_data_reg_valid $end
$var reg 5 < state [4:0] $end
$scope module RX $end
$var wire 1 ' clk_i $end
$var wire 1 = data_bit_cond $end
$var wire 1 ! rst_i $end
$var wire 1 4 rx_done $end
$var wire 1 + rx_en_i $end
$var wire 1 , rx_i $end
$var wire 1 > start_bit_cond $end
$var wire 1 3 stop_bit $end
$var wire 1 ? stop_bit_cond $end
$var wire 1 - tick_i $end
$var reg 4 @ bitcount [3:0] $end
$var reg 4 A counter [3:0] $end
$var reg 8 B data_o [7:0] $end
$var reg 1 C state $end
$scope function next $end
$var reg 1 D next $end
$var reg 1 E rx_en_i $end
$var reg 1 F rx_i $end
$var reg 1 G state $end
$var reg 1 H stop_bit_cond $end
$upscope $end
$upscope $end
$scope module chk $end
$var wire 1 ' clk_i $end
$var wire 40 I data_i [39:0] $end
$var wire 16 J invert [15:0] $end
$var wire 17 K mask_i [16:0] $end
$var wire 1 ! rst_i $end
$var wire 1 / we_i $end
$var wire 16 L xout [15:0] $end
$var wire 1 M serial_data $end
$var wire 1 N rst_ff $end
$var wire 1 O invert_en $end
$var wire 1 P done $end
$var wire 16 Q Q [15:0] $end
$var reg 6 R count [5:0] $end
$var reg 40 S data [39:0] $end
$var reg 16 T out_o [15:0] $end
$var reg 1 0 out_valid_o $end
$var reg 1 U valid $end
$scope module d0 $end
$var wire 1 ' Clk $end
$var wire 1 V D $end
$var wire 1 N rst $end
$var reg 1 W Q $end
$upscope $end
$scope module d1 $end
$var wire 1 ' Clk $end
$var wire 1 X D $end
$var wire 1 N rst $end
$var reg 1 Y Q $end
$upscope $end
$scope module d10 $end
$var wire 1 ' Clk $end
$var wire 1 Z D $end
$var wire 1 N rst $end
$var reg 1 [ Q $end
$upscope $end
$scope module d11 $end
$var wire 1 ' Clk $end
$var wire 1 \ D $end
$var wire 1 N rst $end
$var reg 1 ] Q $end
$upscope $end
$scope module d12 $end
$var wire 1 ' Clk $end
$var wire 1 ^ D $end
$var wire 1 N rst $end
$var reg 1 _ Q $end
$upscope $end
$scope module d13 $end
$var wire 1 ' Clk $end
$var wire 1 ` D $end
$var wire 1 N rst $end
$var reg 1 a Q $end
$upscope $end
$scope module d14 $end
$var wire 1 ' Clk $end
$var wire 1 b D $end
$var wire 1 N rst $end
$var reg 1 c Q $end
$upscope $end
$scope module d15 $end
$var wire 1 ' Clk $end
$var wire 1 d D $end
$var wire 1 N rst $end
$var reg 1 e Q $end
$upscope $end
$scope module d2 $end
$var wire 1 ' Clk $end
$var wire 1 f D $end
$var wire 1 N rst $end
$var reg 1 g Q $end
$upscope $end
$scope module d3 $end
$var wire 1 ' Clk $end
$var wire 1 h D $end
$var wire 1 N rst $end
$var reg 1 i Q $end
$upscope $end
$scope module d4 $end
$var wire 1 ' Clk $end
$var wire 1 j D $end
$var wire 1 N rst $end
$var reg 1 k Q $end
$upscope $end
$scope module d5 $end
$var wire 1 ' Clk $end
$var wire 1 l D $end
$var wire 1 N rst $end
$var reg 1 m Q $end
$upscope $end
$scope module d6 $end
$var wire 1 ' Clk $end
$var wire 1 n D $end
$var wire 1 N rst $end
$var reg 1 o Q $end
$upscope $end
$scope module d7 $end
$var wire 1 ' Clk $end
$var wire 1 p D $end
$var wire 1 N rst $end
$var reg 1 q Q $end
$upscope $end
$scope module d8 $end
$var wire 1 ' Clk $end
$var wire 1 r D $end
$var wire 1 N rst $end
$var reg 1 s Q $end
$upscope $end
$scope module d9 $end
$var wire 1 ' Clk $end
$var wire 1 t D $end
$var wire 1 N rst $end
$var reg 1 u Q $end
$upscope $end
$upscope $end
$upscope $end
$upscope $end
$enddefinitions $end
#0
$dumpvars
0u
0t
0s
0r
0q
0p
0o
0n
0m
0l
0k
0j
0i
0h
0g
0f
0e
0d
0c
0b
0a
0`
0_
0^
0]
0\
0[
0Z
0Y
0X
0W
0V
0U
b0 T
b0 S
b0 R
b0 Q
0P
0O
1N
0M
b0 L
b10001000000100001 K
b0 J
b0 I
xH
xG
xF
xE
xD
0C
b0 B
b0 A
b0 @
0?
0>
0=
b0 <
0;
b0 :
b0 9
08
b0 7
b0 6
b0 5
14
03
b0 2
b0 1
00
0/
b0 .
0-
1,
1+
b0 *
b100100001101001001000010011000111111101 )
b0 (
0'
b0 &
0%
0$
b0 #
0"
0!
$end
#100
b1 &
0D
1F
0G
1E
0H
1'
#200
0'
#300
b10 &
1'
#400
0'
#500
b1 .
1-
1$
b11 &
1'
#600
0'
#700
0$
b100 &
1'
#800
0'
#900
b101 &
1'
#1000
0'
#1100
b110 &
1'
#1200
0'
#1300
b111 &
1'
#1400
0'
#1500
b0 &
1'
#1600
0'
#1700
b1 &
1'
#1800
0'
#1900
b10 &
1'
#2000
0'
#2100
0-
1$
b11 &
1'
#2200
0'
#2300
0$
b100 &
1'
#2400
0'
#2500
b101 &
1'
#2600
0'
#2700
b110 &
1'
#2800
0'
#2900
b111 &
1'
#3000
0'
#3100
b0 &
1'
#3200
0'
#3300
b1 &
1'
#3400
0'
#3500
b10 &
1'
#3600
0'
#3700
b10 .
1-
1$
b11 &
1'
#3800
0'
#3900
0$
b100 &
1'
#4000
0'
#4100
b101 &
1'
#4200
0'
#4300
b110 &
1'
#4400
0'
#4500
b111 &
1'
#4600
0'
#4700
b0 &
1'
#4800
0'
#4900
b1 &
1'
#5000
0'
#5100
b10 &
1'
#5200
0'
#5300
0-
1$
b11 &
1'
#5400
0'
#5500
0$
b100 &
1'
#5600
0'
#5700
b101 &
1'
#5800
0'
#5900
b110 &
1'
#6000
0'
#6100
b111 &
1'
#6200
0'
#6300
b0 &
1'
#6400
0'
#6500
b1 &
1'
#6600
0'
#6700
b10 &
1'
#6800
0'
#6900
b11 .
1-
1$
b11 &
1'
#7000
0'
#7100
0$
b100 &
1'
#7200
0'
#7300
b101 &
1'
#7400
0'
#7500
b110 &
1'
#7600
0'
#7700
b111 &
1'
#7800
0'
#7900
b0 &
1'
#8000
0'
#8100
b1 &
1'
#8200
0'
#8300
b10 &
1'
#8400
0'
#8500
0-
1$
b11 &
1'
#8600
0'
#8700
0$
b100 &
1'
#8800
0'
#8900
b101 &
1'
#9000
0'
#9100
b110 &
1'
#9200
0'
#9300
b111 &
1'
#9400
0'
#9500
b0 &
1'
#9600
0'
#9700
b1 &
1'
#9800
0'
#9900
b10 &
1'
#10000
0'
#10100
b100 .
1-
1$
b11 &
1'
#10200
0'
#10300
0$
b100 &
1'
#10400
0'
#10500
b101 &
1'
#10600
0'
#10700
b110 &
1'
#10800
0'
#10900
b111 &
1'
#11000
0'
#11100
b0 &
1'
#11200
0'
#11300
b1 &
1'
#11400
0'
#11500
b10 &
1'
#11600
0'
#11700
0-
1$
b11 &
1'
#11800
0'
#11900
0$
b100 &
1'
#12000
0'
#12100
b101 &
1'
#12200
0'
#12300
b110 &
1'
#12400
0'
#12500
b111 &
1'
#12600
0'
#12700
b0 &
1'
#12800
0'
#12900
b1 &
1'
#13000
0'
#13100
b10 &
1'
#13200
0'
#13300
b101 .
1-
1$
b11 &
1'
#13400
0'
#13500
0$
b100 &
1'
#13600
0'
#13700
b101 &
1'
#13800
0'
#13900
b110 &
1'
#14000
0'
#14100
b111 &
1'
#14200
0'
#14300
b0 &
1'
#14400
0'
#14500
b1 &
1'
#14600
0'
#14700
b10 &
1'
#14800
0'
#14900
0-
1$
b11 &
1'
#15000
0'
#15100
0$
b100 &
1'
#15200
0'
#15300
b101 &
1'
#15400
0'
#15500
b110 &
1'
#15600
0'
#15700
b111 &
1'
#15800
0'
#15900
b0 &
1'
#16000
0'
#16100
b1 &
1'
#16200
0'
#16300
b10 &
1'
#16400
0'
#16500
b110 .
1-
1$
b11 &
1'
#16600
0'
#16700
0$
b100 &
1'
#16800
0'
#16900
b101 &
1'
#17000
0'
#17100
b110 &
1'
#17200
0'
#17300
b111 &
1'
#17400
0'
#17500
b0 &
1'
#17600
0'
#17700
b1 &
1'
#17800
0'
#17900
b10 &
1'
#18000
0'
#18100
0-
1$
b11 &
1'
#18200
0'
#18300
0$
b100 &
1'
#18400
0'
#18500
b101 &
1'
#18600
0'
#18700
b110 &
1'
#18800
0'
#18900
b111 &
1'
#19000
0'
#19100
b0 &
1'
#19200
0'
#19300
b1 &
1'
#19400
0'
#19500
b10 &
1'
#19600
0'
#19700
b111 .
1-
1$
b11 &
1'
#19800
0'
#19900
0$
b100 &
1'
#20000
0'
#20100
b101 &
1'
#20200
0'
#20300
b110 &
1'
#20400
0'
#20500
b111 &
1'
#20600
0'
#20700
b0 &
1'
#20800
0'
#20900
b1 &
1'
#21000
0'
#21100
b10 &
1'
#21200
0'
#21300
0-
1$
b11 &
1'
#21400
0'
#21500
0$
b100 &
1'
#21600
0'
#21700
b101 &
1'
#21800
0'
#21900
b110 &
1'
#22000
0'
#22100
b111 &
1'
#22200
0'
#22300
b0 &
1'
#22400
0'
#22500
b1 &
1'
#22600
0'
#22700
b10 &
1'
#22800
0'
#22900
b1000 .
1-
1$
b11 &
1'
#23000
0'
#23100
0$
b100 &
1'
#23200
0'
#23300
b101 &
1'
#23400
0'
#23500
b110 &
1'
#23600
0'
#23700
b111 &
1'
#23800
0'
#23900
b0 &
1'
#24000
0'
#24100
b1 &
1'
#24200
0'
#24300
b10 &
1'
#24400
0'
#24500
0-
1$
b11 &
1'
#24600
0'
#24700
0$
b100 &
1'
#24800
0'
#24900
b101 &
1'
#25000
0'
#25100
b110 &
1'
#25200
0'
#25300
b111 &
1'
#25400
0'
#25500
b0 &
1'
#25600
0'
#25700
b1 &
1'
#25800
0'
#25900
b10 &
1'
#26000
0'
#26100
b1001 .
1-
1$
b11 &
1'
#26200
0'
#26300
0$
b100 &
1'
#26400
0'
#26500
b101 &
1'
#26600
0'
#26700
b110 &
1'
#26800
0'
#26900
b111 &
1'
#27000
0'
#27100
b0 &
1'
#27200
0'
#27300
b1 &
1'
#27400
0'
#27500
b10 &
1'
#27600
0'
#27700
0-
1$
b11 &
1'
#27800
0'
#27900
0$
b100 &
1'
#28000
0'
#28100
b101 &
1'
#28200
0'
#28300
b110 &
1'
#28400
0'
#28500
b111 &
1'
#28600
0'
#28700
b0 &
1'
#28800
0'
#28900
b1 &
1'
#29000
0'
#29100
b10 &
1'
#29200
0'
#29300
b1010 .
1-
1$
b11 &
1'
#29400
0'
#29500
0$
b100 &
1'
#29600
0'
#29700
b101 &
1'
#29800
0'
#29900
b110 &
1'
#30000
0'
#30100
b111 &
1'
#30200
0'
#30300
b0 &
1'
#30400
0'
#30500
b1 &
1'
#30600
0'
#30700
b10 &
1'
#30800
0'
#30900
0-
1$
b11 &
1'
#31000
0'
#31100
0$
b100 &
1'
#31200
0'
#31300
b101 &
1'
#31400
0'
#31500
b110 &
1'
#31600
0'
#31700
b111 &
1'
#31800
0'
#31900
b0 &
1'
#32000
0'
#32100
b1 &
1'
#32200
0'
#32300
b10 &
1'
#32400
0'
#32500
b1011 .
1-
1$
b11 &
1'
#32600
0'
#32700
0$
b100 &
1'
#32800
0'
#32900
b101 &
1'
#33000
0'
#33100
b110 &
1'
#33200
0'
#33300
b111 &
1'
#33400
0'
#33500
b0 &
1'
#33600
0'
#33700
b1 &
1'
#33800
0'
#33900
b10 &
1'
#34000
0'
#34100
0-
1$
b11 &
1'
#34200
0'
#34300
0$
b100 &
1'
#34400
0'
#34500
b101 &
1'
#34600
0'
#34700
b110 &
1'
#34800
0'
#34900
b111 &
1'
#35000
0'
#35100
b0 &
1'
#35200
0'
#35300
b1 &
1'
#35400
0'
#35500
b10 &
1'
#35600
0'
#35700
b1100 .
1-
1$
b11 &
1'
#35800
0'
#35900
0$
b100 &
1'
#36000
0'
#36100
b101 &
1'
#36200
0'
#36300
b110 &
1'
#36400
0'
#36500
b111 &
1'
#36600
0'
#36700
b0 &
1'
#36800
0'
#36900
b1 &
1'
#37000
0'
#37100
b10 &
1'
#37200
0'
#37300
0-
1$
b11 &
1'
#37400
0'
#37500
0$
b100 &
1'
#37600
0'
#37700
b101 &
1'
#37800
0'
#37900
b110 &
1'
#38000
0'
#38100
b111 &
1'
#38200
0'
#38300
b0 &
1'
#38400
0'
#38500
b1 &
1'
#38600
0'
#38700
b10 &
1'
#38800
0'
#38900
b1101 .
1-
1$
b11 &
1'
#39000
0'
#39100
0$
b100 &
1'
#39200
0'
#39300
b101 &
1'
#39400
0'
#39500
b110 &
1'
#39600
0'
#39700
b111 &
1'
#39800
0'
#39900
b0 &
1'
#40000
0'
#40100
b1 &
1'
#40200
0'
#40300
b10 &
1'
#40400
0'
#40500
0-
1$
b11 &
1'
#40600
0'
#40700
0$
b100 &
1'
#40800
0'
#40900
b101 &
1'
#41000
0'
#41100
b110 &
1'
#41200
0'
#41300
b111 &
1'
#41400
0'
#41500
b0 &
1'
#41600
0'
#41700
b1 &
1'
#41800
0'
#41900
b10 &
1'
#42000
0'
#42100
b1110 .
1-
1$
b11 &
1'
#42200
0'
#42300
0$
b100 &
1'
#42400
0'
#42500
b101 &
1'
#42600
0'
#42700
b110 &
1'
#42800
0'
#42900
b111 &
1'
#43000
0'
#43100
b0 &
1'
#43200
0'
#43300
b1 &
1'
#43400
0'
#43500
b10 &
1'
#43600
0'
#43700
0-
1$
b11 &
1'
#43800
0'
#43900
0$
b100 &
1'
#44000
0'
#44100
b101 &
1'
#44200
0'
#44300
b110 &
1'
#44400
0'
#44500
b111 &
1'
#44600
0'
#44700
b0 &
1'
#44800
0'
#44900
b1 &
1'
#45000
0'
#45100
b10 &
1'
#45200
0'
#45300
b1 (
1%
b1111 .
1-
1$
b11 &
1'
#45400
0'
#45500
0$
b100 &
1'
#45600
0'
#45700
b101 &
1'
#45800
0'
#45900
b110 &
1'
#46000
0'
#46100
b111 &
1'
#46200
0'
#46300
b0 &
1'
#46400
0'
#46500
b1 &
1'
#46600
0'
#46700
b10 &
1'
#46800
0'
#46900
0-
1$
b11 &
1'
#47000
0'
#47100
0$
b100 &
1'
#47200
0'
#47300
b101 &
1'
#47400
0'
#47500
b110 &
1'
#47600
0'
#47700
b111 &
1'
#47800
0'
#47900
b0 &
1'
#48000
0'
#48100
b1 &
1'
#48200
0'
#48300
b10 &
1'
#48400
0'
#48500
0%
b0 .
1-
1$
b11 &
1'
#48600
0'
#48700
0$
b100 &
1'
#48800
0'
#48900
b101 &
1'
#49000
0'
#49100
b110 &
1'
#49200
0'
#49300
b111 &
1'
#49400
0'
#49500
b0 &
1'
#49600
0'
#49700
b1 &
1'
#49800
0'
#49900
b10 &
1'
#50000
0'
#50100
0-
1$
b11 &
1'
#50200
0'
#50300
0$
b100 &
1'
#50400
0'
#50500
b101 &
1'
#50600
0'
#50700
b110 &
1'
#50800
0'
#50900
b111 &
1'
#51000
0'
#51100
b0 &
1'
#51200
0'
#51300
b1 &
1'
#51400
0'
#51500
b10 &
1'
#51600
0'
#51700
b1 .
1-
1$
b11 &
1'
#51800
0'
#51900
0$
b100 &
1'
#52000
0'
#52100
b101 &
1'
#52200
0'
#52300
b110 &
1'
#52400
0'
#52500
b111 &
1'
#52600
0'
#52700
b0 &
1'
#52800
0'
#52900
b1 &
1'
#53000
0'
#53100
b10 &
1'
#53200
0'
#53300
0-
1$
b11 &
1'
#53400
0'
#53500
0$
b100 &
1'
#53600
0'
#53700
b101 &
1'
#53800
0'
#53900
b110 &
1'
#54000
0'
#54100
b111 &
1'
#54200
0'
#54300
b0 &
1'
#54400
0'
#54500
b1 &
1'
#54600
0'
#54700
b10 &
1'
#54800
0'
#54900
b10 .
1-
1$
b11 &
1'
#55000
0'
#55100
0$
b100 &
1'
#55200
0'
#55300
b101 &
1'
#55400
0'
#55500
b110 &
1'
#55600
0'
#55700
b111 &
1'
#55800
0'
#55900
b0 &
1'
#56000
0'
#56100
b1 &
1'
#56200
0'
#56300
b10 &
1'
#56400
0'
#56500
0-
1$
b11 &
1'
#56600
0'
#56700
0$
b100 &
1'
#56800
0'
#56900
b101 &
1'
#57000
0'
#57100
b110 &
1'
#57200
0'
#57300
b111 &
1'
#57400
0'
#57500
b0 &
1'
#57600
0'
#57700
b1 &
1'
#57800
0'
#57900
b10 &
1'
#58000
0'
#58100
b11 .
1-
1$
b11 &
1'
#58200
0'
#58300
0$
b100 &
1'
#58400
0'
#58500
b101 &
1'
#58600
0'
#58700
b110 &
1'
#58800
0'
#58900
b111 &
1'
#59000
0'
#59100
b0 &
1'
#59200
0'
#59300
b1 &
1'
#59400
0'
#59500
b10 &
1'
#59600
0'
#59700
0-
1$
b11 &
1'
#59800
0'
#59900
0$
b100 &
1'
#60000
0'
#60100
b101 &
1'
#60200
0'
#60300
b110 &
1'
#60400
0'
#60500
b111 &
1'
#60600
0'
#60700
b0 &
1'
#60800
0'
#60900
b1 &
1'
#61000
0'
#61100
b10 &
1'
#61200
0'
#61300
b100 .
1-
1$
b11 &
1'
#61400
0'
#61500
0$
b100 &
1'
#61600
0'
#61700
b101 &
1'
#61800
0'
#61900
b110 &
1'
#62000
0'
#62100
b111 &
1'
#62200
0'
#62300
b0 &
1'
#62400
0'
#62500
b1 &
1'
#62600
0'
